b2b_rms_sdk/__init__.py
b2b_rms_sdk/models.py
b2b_rms_sdk/services/__init__.py
b2b_rms_sdk/services/routes.py
tests/__init__.py
tests/factories.py
tests/test_models.py
b2b_rms_sdk-0.0.5.dist-info/METADATA
b2b_rms_sdk-0.0.5.dist-info/WHEEL
b2b_rms_sdk-0.0.5.dist-info/top_level.txt
b2b_rms_sdk-0.0.5.dist-info/RECORD
