Metadata-Version: 2.1
Name: b2b-rms-sdk
Version: 0.0.5
Summary: Helper SDK for b2b_rms apis
Home-page: https://github.com/shuttl-tech/b2b_rms_sdk
Author: Jayesh Hathila
Author-email: jayesh.hathila@shuttl.com
License: MIT
Platform: UNKNOWN
Classifier: Programming Language :: Python :: 3.7
Requires-Dist: pyshuttlis
Requires-Dist: requests
Provides-Extra: test
Requires-Dist: pytest ; extra == 'test'
Requires-Dist: pytest-runner ; extra == 'test'
Requires-Dist: pytest-cov ; extra == 'test'
Requires-Dist: pytest-pep8 ; extra == 'test'
